[{"id":1,"first_name":"Louisa","last_name":"Derks","graduation_year":2024,"address":"19242 Hoard Junction","city":"Barakī Barak","zip":null,"state":null,"county":"Afghanistan","avatar":"https://robohash.org/reruminet.png?size=50x50&set=set1"},
{"id":2,"first_name":"Marwin","last_name":"Godsell","graduation_year":2024,"address":"133 Butternut Place","city":"Kafir Qala","zip":null,"state":null,"county":"Afghanistan","avatar":"https://robohash.org/autquisat.png?size=50x50&set=set1"},
{"id":3,"first_name":"Adair","last_name":"Stiger","graduation_year":2030,"address":"450 Menomonie Road","city":"Wuṯahpūr","zip":null,"state":null,"county":"Afghanistan","avatar":"https://robohash.org/namodioneque.png?size=50x50&set=set1"},
{"id":4,"first_name":"Heda","last_name":"Hurcombe","graduation_year":2022,"address":"843 Marcy Lane","city":"Maymana","zip":null,"state":null,"county":"Afghanistan","avatar":"https://robohash.org/veniamquoquia.png?size=50x50&set=set1"},
{"id":5,"first_name":"Svend","last_name":"Brigge","graduation_year":2023,"address":"234 Quincy Junction","city":"Mīrābād","zip":null,"state":null,"county":"Afghanistan","avatar":"https://robohash.org/eossuscipitnihil.png?size=50x50&set=set1"},
{"id":6,"first_name":"Vassily","last_name":"Halbert","graduation_year":2024,"address":"3129 Spenser Place","city":"Ghazni","zip":null,"state":null,"county":"Afghanistan","avatar":"https://robohash.org/possimustemporibuseos.png?size=50x50&set=set1"},
{"id":7,"first_name":"Neddy","last_name":"Wasselin","graduation_year":2022,"address":"2 Sommers Lane","city":"Rustāq","zip":null,"state":null,"county":"Afghanistan","avatar":"https://robohash.org/commodiestet.png?size=50x50&set=set1"},
{"id":8,"first_name":"Saunderson","last_name":"Lau","graduation_year":2024,"address":"4 Monument Hill","city":"Rustāq","zip":null,"state":null,"county":"Afghanistan","avatar":"https://robohash.org/errorperferendisest.png?size=50x50&set=set1"},
{"id":9,"first_name":"Lazarus","last_name":"Ralph","graduation_year":2027,"address":"4775 Golden Leaf Lane","city":"Khudāydād Khēl","zip":null,"state":null,"county":"Afghanistan","avatar":"https://robohash.org/temporavoluptatessit.png?size=50x50&set=set1"},
{"id":10,"first_name":"Alexis","last_name":"Wondraschek","graduation_year":2028,"address":"1 Crownhardt Parkway","city":"Aībak","zip":null,"state":null,"county":"Afghanistan","avatar":"https://robohash.org/suscipitquierror.png?size=50x50&set=set1"},
{"id":11,"first_name":"Beau","last_name":"Whapham","graduation_year":2029,"address":"18450 Sutteridge Alley","city":"Fayzabad","zip":null,"state":null,"county":"Afghanistan","avatar":"https://robohash.org/quaeratvoluptasperferendis.png?size=50x50&set=set1"},
{"id":12,"first_name":"Brittni","last_name":"Schroeder","graduation_year":2022,"address":"1 Menomonie Lane","city":"Salām Khēl","zip":null,"state":null,"county":"Afghanistan","avatar":"https://robohash.org/voluptasautsaepe.png?size=50x50&set=set1"},
{"id":13,"first_name":"Inna","last_name":"Christopher","graduation_year":2029,"address":"243 Hoard Point","city":"Qal‘ah-ye Kūf","zip":null,"state":null,"county":"Afghanistan","avatar":"https://robohash.org/quisestconsequatur.png?size=50x50&set=set1"},
{"id":14,"first_name":"Maurie","last_name":"Cheevers","graduation_year":2025,"address":"068 Bartillon Circle","city":"Ārt Khwājah","zip":null,"state":null,"county":"Afghanistan","avatar":"https://robohash.org/nequetemporeaut.png?size=50x50&set=set1"},
{"id":15,"first_name":"Pamela","last_name":"Bente","graduation_year":2022,"address":"337 Anthes Place","city":"Asadābād","zip":null,"state":null,"county":"Afghanistan","avatar":"https://robohash.org/perferendisitaqueipsam.png?size=50x50&set=set1"},
{"id":16,"first_name":"Inigo","last_name":"Giblett","graduation_year":2026,"address":"517 Marquette Court","city":"Shahrak","zip":null,"state":null,"county":"Afghanistan","avatar":"https://robohash.org/nostrumeterror.png?size=50x50&set=set1"},
{"id":17,"first_name":"Raynard","last_name":"Tarbatt","graduation_year":2028,"address":"5 Drewry Street","city":"Deh-e Now","zip":null,"state":null,"county":"Afghanistan","avatar":"https://robohash.org/nequecorruptivoluptas.png?size=50x50&set=set1"},
{"id":18,"first_name":"Lynne","last_name":"Bacchus","graduation_year":2024,"address":"1863 Fulton Drive","city":"Shahrak","zip":null,"state":null,"county":"Afghanistan","avatar":"https://robohash.org/cumquedolorquas.png?size=50x50&set=set1"},
{"id":19,"first_name":"Evania","last_name":"Strutt","graduation_year":2026,"address":"24 Larry Pass","city":"Ḩājī Khēl","zip":null,"state":null,"county":"Afghanistan","avatar":"https://robohash.org/solutaporrout.png?size=50x50&set=set1"},
{"id":20,"first_name":"Letti","last_name":"Headan","graduation_year":2027,"address":"27 Kropf Trail","city":"Rustāq","zip":null,"state":null,"county":"Afghanistan","avatar":"https://robohash.org/voluptasutpraesentium.png?size=50x50&set=set1"},
{"id":21,"first_name":"Sibelle","last_name":"Meenehan","graduation_year":2030,"address":"5 Reinke Road","city":"Maymana","zip":null,"state":null,"county":"Afghanistan","avatar":"https://robohash.org/pariatureteum.png?size=50x50&set=set1"},
{"id":22,"first_name":"Perla","last_name":"McAulay","graduation_year":2026,"address":"58751 Southridge Park","city":"Dū Laīnah","zip":null,"state":null,"county":"Afghanistan","avatar":"https://robohash.org/perferendiseumearum.png?size=50x50&set=set1"},
{"id":23,"first_name":"Lusa","last_name":"Halworth","graduation_year":2025,"address":"82010 Prairieview Road","city":"Baghlān","zip":null,"state":null,"county":"Afghanistan","avatar":"https://robohash.org/sintrerumporro.png?size=50x50&set=set1"},
{"id":24,"first_name":"Bendite","last_name":"Mattiazzi","graduation_year":2025,"address":"48 Autumn Leaf Pass","city":"Qala i Naw","zip":null,"state":null,"county":"Afghanistan","avatar":"https://robohash.org/corruptiautemeum.png?size=50x50&set=set1"},
{"id":25,"first_name":"Inger","last_name":"Geal","graduation_year":2027,"address":"32756 Blue Bill Park Trail","city":"Qala i Naw","zip":null,"state":null,"county":"Afghanistan","avatar":"https://robohash.org/nihilcumet.png?size=50x50&set=set1"},
{"id":26,"first_name":"Bren","last_name":"Markovic","graduation_year":2026,"address":"5787 Meadow Vale Crossing","city":"Dū Qal‘ah","zip":null,"state":null,"county":"Afghanistan","avatar":"https://robohash.org/essequasivel.png?size=50x50&set=set1"},
{"id":27,"first_name":"Koralle","last_name":"Keyhoe","graduation_year":2023,"address":"985 Waxwing Circle","city":"Shibirghān","zip":null,"state":null,"county":"Afghanistan","avatar":"https://robohash.org/atqueremratione.png?size=50x50&set=set1"},
{"id":28,"first_name":"Taylor","last_name":"Marshland","graduation_year":2026,"address":"7 Di Loreto Hill","city":"Panjāb","zip":null,"state":null,"county":"Afghanistan","avatar":"https://robohash.org/autrerumoccaecati.png?size=50x50&set=set1"},
{"id":29,"first_name":"Mervin","last_name":"Nisard","graduation_year":2029,"address":"07 Packers Place","city":"Pul-e Khumrī","zip":null,"state":null,"county":"Afghanistan","avatar":"https://robohash.org/aliquamesseitaque.png?size=50x50&set=set1"},
{"id":30,"first_name":"Evy","last_name":"Doby","graduation_year":2025,"address":"96537 Autumn Leaf Terrace","city":"Mīrābād","zip":null,"state":null,"county":"Afghanistan","avatar":"https://robohash.org/officiafaciliseos.png?size=50x50&set=set1"}]